{
  "chummer": {
    "attributes": {
      "{http://www.w3.org/2001/XMLSchema-instance}schemaLocation": "http://www.w3.org/2001/XMLSchema mentors.xsd"
    },
    "categories": {
      "category": "Resonance"
    },
    "mentors": {
      "mentor": [
        {
          "id": "acadd628-ebb5-4c79-a3c2-953ce7fa1885",
          "name": "01 (The World Tree)",
          "category": "Resonance",
          "advantage": "If a follower of 01 has at least one mark on a target, they may act as if they have an extra mark on it.",
          "disadvantage": "\u20131 limit and \u20131 dice pool penalty when acting only in AR.",
          "source": "KC",
          "page": "103"
        },
        {
          "id": "46f88748-8c6c-4230-ad59-2eccb463cc35",
          "name": "Architect",
          "category": "Resonance",
          "advantage": "+1 limit and +1 dice pool bonus for Edit actions.",
          "disadvantage": "\u20131 limit and \u20131 dice for Snoop actions.",
          "bonus": {
            "specificskill": {
              "name": "Computer",
              "bonus": "1",
              "condition": "Edit File"
            }
          },
          "source": "KC",
          "page": "103"
        },
        {
          "id": "690ccad8-3f42-4d62-a358-e099747fc4e4",
          "name": "Archivist (The Record Keeper)",
          "category": "Resonance",
          "advantage": "+1 limit and +1 dice pool bonus for Browse actions and digital legwork.",
          "disadvantage": "\u20131 limit for Edit actions designed to destroy data.",
          "bonus": {
            "specificskill": {
              "name": "Computer",
              "bonus": "1",
              "condition": "Matrix Search"
            }
          },
          "source": "KC",
          "page": "177"
        },
        {
          "id": "117e7c69-abea-4637-b5e7-3a927ae0ad60",
          "name": "Black Hat (The Cracker)",
          "category": "Resonance",
          "advantage": "+2 limit for gaining marks on a target.",
          "disadvantage": "-1 limit and \u20131 die when setting a Data Bomb.",
          "source": "KC",
          "page": "103"
        },
        {
          "id": "b74d032e-5d39-4e4a-b043-0707ffa00b5e",
          "name": "Daedalus (The Inventor)",
          "category": "Resonance",
          "advantage": "+1 dice pool bonus for Hardware tests, +1 limit on Pilot skill tests when jumped in.",
          "disadvantage": "\u20131 dice and limit for all actions in the Deep Resonance.",
          "bonus": {
            "specificskill": {
              "name": "Hardware",
              "bonus": "1"
            }
          },
          "source": "KC",
          "page": "103"
        },
        {
          "id": "c45c123c-06c7-42b3-a2ee-01e37f2f7bf8",
          "name": "Delphi (The Oracle)",
          "category": "Resonance",
          "advantage": "+1 bonus to dice pool and limit when threading complex forms.",
          "disadvantage": "\u20132 modifier to the technomancer's Initiative Score.",
          "bonus": {
            "actiondicepool": {
              "name": "Threading",
              "val": "1"
            },
            "initiative": "-2",
            "matrixinitiative": "-2"
          },
          "source": "KC",
          "page": "104"
        },
        {
          "id": "df42911f-0542-4fae-80d1-39573547ff68",
          "name": "Intrusion Countermeasure (The Guardian)",
          "category": "Resonance",
          "advantage": "+1 bonus to dice pool and limit in cybercombat, +1 to firewall.",
          "disadvantage": "\u20131 dice pool penalty when attacking IC in cybercombat.",
          "bonus": {
            "livingpersona": {
              "firewall": "1"
            },
            "specificskill": {
              "name": "Cybercombat",
              "bonus": "1",
              "condition": "Not against IC"
            }
          },
          "source": "KC",
          "page": "104"
        },
        {
          "id": "da2f3bad-d934-461a-aa92-60fc6e5c3ef7",
          "name": "Probe (The Scout)",
          "category": "Resonance",
          "advantage": "+2 dice pool bonus and +1 limit on all actions when directly connected to an isolated system.",
          "disadvantage": "\u20131 limit penalty when logged into more than one grid.",
          "source": "KC",
          "page": "104"
        },
        {
          "id": "de755412-5cae-4859-880f-75a7bd68d5a4",
          "name": "Shooter (The Soldier)",
          "category": "Resonance",
          "advantage": "+1 bonus to dice pool and limit in cybercombat, +1 limit to all attack actions (physical and Matrix)",
          "disadvantage": "\u20132 dice pool penalty and \u20131 limit when compiling sprites.",
          "bonus": {
            "specificskill": [
              {
                "name": "Cybercombat",
                "bonus": "1"
              },
              {
                "name": "Compiling",
                "bonus": "-2"
              }
            ],
            "weaponskillaccuracy": [
              {
                "name": "Archery",
                "value": "1"
              },
              {
                "name": "Automatics",
                "value": "1"
              },
              {
                "name": "Blades",
                "value": "1"
              },
              {
                "name": "Clubs",
                "value": "1"
              },
              {
                "name": "Exotic Melee Weapon",
                "value": "1"
              },
              {
                "name": "Exotic Ranged Weapon",
                "value": "1"
              },
              {
                "name": "Gunnery",
                "value": "1"
              },
              {
                "name": "Heavy Weapons",
                "value": "1"
              },
              {
                "name": "Longarms",
                "value": "1"
              },
              {
                "name": "Pistols",
                "value": "1"
              },
              {
                "name": "Throwing Weapons",
                "value": "1"
              },
              {
                "name": "Unarmed Combat",
                "value": "1"
              }
            ]
          },
          "source": "KC",
          "page": "104"
        }
      ]
    }
  }
}